{"chunk_definitions":[{"row":22,"row_count":1,"visible":true,"expansion_state":0,"options":{"engine":"r","label":"unnamed-chunk-1","dev":"png"},"document_id":"684A971A","chunk_id":"cx33wlwok2xjq","chunk_label":"unnamed-chunk-1"},{"row":37,"row_count":1,"visible":true,"expansion_state":0,"options":{"engine":"r","label":"unnamed-chunk-4","dev":"png"},"document_id":"684A971A","chunk_id":"cgim7suge8nkf","chunk_label":"unnamed-chunk-2"},{"row":102,"row_count":1,"visible":true,"expansion_state":0,"options":{"engine":"r","label":"unnamed-chunk-3","dev":"png"},"document_id":"684A971A","chunk_id":"chlwcpktaeon3","chunk_label":"unnamed-chunk-3"},{"row":381,"row_count":1,"visible":true,"expansion_state":0,"options":{"engine":"r","label":"unnamed-chunk-35","dev":"png"},"document_id":"684A971A","chunk_id":"c9vbjzkmd3e5d","chunk_label":"unnamed-chunk-18"},{"row":166,"row_count":1,"visible":true,"expansion_state":0,"options":{"engine":"r","label":"unnamed-chunk-2","dev":"png"},"document_id":"684A971A","chunk_id":"c68ausdidnx31","chunk_label":"unnamed-chunk-6"},{"row":288,"row_count":1,"visible":true,"expansion_state":0,"options":{"engine":"r","label":"unnamed-chunk-10","dev":"png"},"document_id":"684A971A","chunk_id":"c5dw3eb0dhuna","chunk_label":"unnamed-chunk-13"},{"row":302,"row_count":1,"visible":true,"expansion_state":0,"options":{"engine":"r","label":"unnamed-chunk-31","dev":"png"},"document_id":"684A971A","chunk_id":"c69rr9smwkn7w","chunk_label":"unnamed-chunk-14"},{"row":318,"row_count":1,"visible":true,"expansion_state":0,"options":{"engine":"r","label":"unnamed-chunk-15","dev":"png"},"document_id":"684A971A","chunk_id":"cg38jjllhkfm4","chunk_label":"unnamed-chunk-15"},{"row":606,"row_count":1,"visible":true,"expansion_state":0,"options":{"engine":"r","label":"unnamed-chunk-19","dev":"png"},"document_id":"684A971A","chunk_id":"cw1em832nboqn","chunk_label":"unnamed-chunk-30"},{"row":816,"row_count":1,"visible":true,"expansion_state":0,"options":{"engine":"r","label":"unnamed-chunk-23","dev":"png"},"document_id":"684A971A","chunk_id":"cfaxpdi5aigkx","chunk_label":"unnamed-chunk-42"},{"row":890,"row_count":1,"visible":true,"expansion_state":0,"options":{"engine":"r","label":"unnamed-chunk-33","dev":"png"},"document_id":"684A971A","chunk_id":"c9rmro9ab0wwp","chunk_label":"unnamed-chunk-43"},{"row":1288,"row_count":1,"visible":true,"expansion_state":0,"options":{"engine":"r","label":"unnamed-chunk-34","dev":"png"},"document_id":"684A971A","chunk_id":"cebyxalfzi55y","chunk_label":"unnamed-chunk-55"}],"doc_write_time":1737643591}